LICENSE
MANIFEST.in
README.rst
requirements.txt
setup.py
vanilla/__init__.py
vanilla/core.py
vanilla/exception.py
vanilla/http.py
vanilla/io.py
vanilla/message.py
vanilla/meta.py
vanilla/poll.py
vanilla/process.py
vanilla/signal.py
vanilla/tcp.py
vanilla/thread.py
vanilla/udp.py
vanilla.egg-info/PKG-INFO
vanilla.egg-info/SOURCES.txt
vanilla.egg-info/dependency_links.txt
vanilla.egg-info/requires.txt
vanilla.egg-info/top_level.txt