Metadata-Version: 1.0
Name: vanilla
Version: 0.1.13
Summary: Straightforward concurrency for Python http://vanillapy.readthedocs.org/
Home-page: https://github.com/cablehead/vanilla
Author: Andy Gayton
Author-email: andy@thecablelounge.com
License: MIT
Platform: UNKNOWN
